setup.py
matrix_opeartions/__init__.py
matrix_opeartions/python_code.py
matrix_operations.egg-info/PKG-INFO
matrix_operations.egg-info/SOURCES.txt
matrix_operations.egg-info/dependency_links.txt
matrix_operations.egg-info/not-zip-safe
matrix_operations.egg-info/top_level.txt