Metadata-Version: 1.0
Name: matrix-operations
Version: 0.1.0
Summary: various matrix operations
Home-page: UNKNOWN
Author: UNKNOWN
Author-email: UNKNOWN
License: UNKNOWN
Platform: UNKNOWN
